{
  "profileName": "standard",
  "minBet": 10,
  "maxBet": 1000,
  "volatility": "medium",
  "rtp": 0.96,
  "paytable": {
    "TRIDENT": {
      "8": 1,
      "10": 4,
      "12": 52
    },
    "PEARL": {
      "8": 1,
      "10": 7,
      "12": 24
    },
    "SHELL": {
      "8": 2,
      "10": 3,
      "12": 59
    },
    "WILD": {
      "8": 2,
      "10": 6,
      "12": 48
    },
    "ANKH": {
      "8": 2,
      "10": 7,
      "12": 58
    },
    "EYE": {
      "8": 2,
      "10": 7,
      "12": 27
    },
    "SCARAB": {
      "8": 2,
      "10": 5,
      "12": 38
    }
  }
}